sphinx_hep_pdgref/__init__.py
sphinx_hep_pdgref/entry.py
sphinx_hep_pdgref/py.typed
sphinx_hep_pdgref/role.py
sphinx_hep_pdgref/url.py
sphinx_hep_pdgref-0.2.1.dist-info/LICENSE
sphinx_hep_pdgref-0.2.1.dist-info/METADATA
sphinx_hep_pdgref-0.2.1.dist-info/WHEEL
sphinx_hep_pdgref-0.2.1.dist-info/top_level.txt
sphinx_hep_pdgref-0.2.1.dist-info/RECORD
